huaweicloudsdkrfs/__init__.py
huaweicloudsdkrfs/v1/__init__.py
huaweicloudsdkrfs/v1/rfs_async_client.py
huaweicloudsdkrfs/v1/rfs_client.py
huaweicloudsdkrfs/v1/model/__init__.py
huaweicloudsdkrfs/v1/model/administration_agency_name_primitive_type_holder.py
huaweicloudsdkrfs/v1/model/administration_agency_urn_primitive_type_holder.py
huaweicloudsdkrfs/v1/model/agencies_primitive_type_holder.py
huaweicloudsdkrfs/v1/model/agency.py
huaweicloudsdkrfs/v1/model/apply_execution_plan_request.py
huaweicloudsdkrfs/v1/model/apply_execution_plan_request_body.py
huaweicloudsdkrfs/v1/model/apply_execution_plan_response.py
huaweicloudsdkrfs/v1/model/base_template.py
huaweicloudsdkrfs/v1/model/base_template_body.py
huaweicloudsdkrfs/v1/model/base_template_version.py
huaweicloudsdkrfs/v1/model/call_identity_primitive_type_holder.py
huaweicloudsdkrfs/v1/model/configuration_primitive_type_holder.py
huaweicloudsdkrfs/v1/model/configuration_primitive_type_holder_configuration.py
huaweicloudsdkrfs/v1/model/continue_deploy_stack_request.py
huaweicloudsdkrfs/v1/model/continue_deploy_stack_request_body.py
huaweicloudsdkrfs/v1/model/continue_deploy_stack_response.py
huaweicloudsdkrfs/v1/model/continue_rollback_stack_request.py
huaweicloudsdkrfs/v1/model/continue_rollback_stack_request_body.py
huaweicloudsdkrfs/v1/model/continue_rollback_stack_response.py
huaweicloudsdkrfs/v1/model/create_execution_plan_request.py
huaweicloudsdkrfs/v1/model/create_execution_plan_request_body.py
huaweicloudsdkrfs/v1/model/create_execution_plan_response.py
huaweicloudsdkrfs/v1/model/create_private_hook_request.py
huaweicloudsdkrfs/v1/model/create_private_hook_request_body.py
huaweicloudsdkrfs/v1/model/create_private_hook_response.py
huaweicloudsdkrfs/v1/model/create_private_hook_version_request.py
huaweicloudsdkrfs/v1/model/create_private_hook_version_request_body.py
huaweicloudsdkrfs/v1/model/create_private_hook_version_response.py
huaweicloudsdkrfs/v1/model/create_private_module_request.py
huaweicloudsdkrfs-3.1.184.dist-info/METADATA
huaweicloudsdkrfs-3.1.184.dist-info/WHEEL
huaweicloudsdkrfs-3.1.184.dist-info/licenses/LICENSE
huaweicloudsdkrfs-3.1.184.dist-info/RECORD
